auth.py
cyral_auth.py
sso.py
cyral_auth-0.2.dist-info/METADATA
cyral_auth-0.2.dist-info/WHEEL
cyral_auth-0.2.dist-info/entry_points.txt
cyral_auth-0.2.dist-info/top_level.txt
cyral_auth-0.2.dist-info/RECORD
